wiseAI/__init__.py
wiseAI/models/__init__.py
wiseAI/models/contrib/__init__.py
wiseAI/models/contrib/automl_binary.py
wiseAI/models/contrib/automl_multiclass.py
wiseAI/models/contrib/automl_multilabel.py
wiseAI/utils/__init__.py
wiseAI/utils/autobinary_loader.py
wiseAI/utils/automulticlass_loader.py
wiseAI/utils/autosampling.py
wiseAI-1.1.0.dist-info/LICENSE
wiseAI-1.1.0.dist-info/METADATA
wiseAI-1.1.0.dist-info/WHEEL
wiseAI-1.1.0.dist-info/top_level.txt
wiseAI-1.1.0.dist-info/RECORD
