Metadata-Version: 2.1
Name: wiseAI
Version: 1.1.0
Summary: Private library using Web3
Home-page: https://github.com/kyu90/web3_ml
Author: kyunam
Author-email: rbska56455@gmail.com
Classifier: Programming Language :: Python :: 3
Classifier: License :: OSI Approved :: MIT License
Classifier: Operating System :: OS Independent
Requires-Python: >=3.7
License-File: LICENSE
Requires-Dist: autogluon==0.5.0
Requires-Dist: numpy<1.23,>=1.21
